{
  "db_name": "PostgreSQL",
  "query": "SELECT id, name, product_type as \"product_type: ProductType\" FROM products WHERE id = $1",
  "describe": {
    "columns": [
      {
        "ordinal": 0,
        "name": "id",
        "type_info": "Int8"
      },
      {
        "ordinal": 1,
        "name": "name",
        "type_info": "Varchar"
      },
      {
        "ordinal": 2,
        "name": "product_type: ProductType",
        "type_info": {
          "Custom": {
            "name": "product_type",
            "kind": {
              "Enum": [
                "colddrink",
                "hotdrink"
              ]
            }
          }
        }
      }
    ],
    "parameters": {
      "Left": [
        "Int8"
      ]
    },
    "nullable": [
      false,
      false,
      false
    ]
  },
  "hash": "7e331ba7c771785dcc0c1eac796123d5d5ee267127608e8f4fa83992d44c3f49"
}
